woki/__init__.py
woki/woki.py
woki-0.0.1.dist-info/METADATA
woki-0.0.1.dist-info/WHEEL
woki-0.0.1.dist-info/top_level.txt
woki-0.0.1.dist-info/RECORD
