Metadata-Version: 2.1
Name: woki
Version: 0.0.1
Summary: A small package to search wikipedia
Home-page: https://github.com/ujalajha43/woki
Author: Ujala Jha
Author-email: jhaujala43@gmail.com
License: UNKNOWN
Platform: UNKNOWN
Classifier: Programming Language :: Python :: 3
Classifier: License :: OSI Approved :: MIT License
Classifier: Operating System :: OS Independent
Requires-Dist: wikipedia
